gable/__init__.py
gable/api/client.py
gable/cli/__init__.py
gable/cli/__main__.py
gable/cli/cli_setup.py
gable/cli/client.py
gable/cli/commands/__init__.py
gable/cli/commands/asset_plugins/__init__.py
gable/cli/commands/asset_plugins/avro.py
gable/cli/commands/asset_plugins/baseclass.py
gable/cli/commands/asset_plugins/json_schema.py
gable/cli/commands/asset_plugins/kotlin.py
gable/cli/commands/asset_plugins/mssql.py
gable/cli/commands/asset_plugins/mysql.py
gable/cli/commands/asset_plugins/postgres.py
gable/cli/commands/asset_plugins/protobuf.py
gable/cli/commands/asset_plugins/pyspark.py
gable/cli/commands/asset_plugins/python.py
gable/cli/commands/asset_plugins/sca_prime.py
gable/cli/commands/asset_plugins/typescript.py
gable/cli/commands/auth.py
gable/cli/commands/contract.py
gable/cli/commands/data_asset.py
gable/cli/commands/data_asset_check.py
gable/cli/commands/data_asset_check_plugin.py
gable/cli/commands/data_asset_create_contracts.py
gable/cli/commands/data_asset_delete.py
gable/cli/commands/data_asset_list.py
gable/cli/commands/data_asset_register.py
gable/cli/commands/data_asset_register_plugin.py
gable/cli/commands/data_asset_show.py
gable/cli/commands/debug.py
gable/cli/commands/lineage.py
gable/cli/commands/lineage_check.py
gable/cli/commands/lineage_enrich.py
gable/cli/commands/lineage_export.py
gable/cli/commands/lineage_register.py
gable/cli/commands/lineage_scan.py
gable/cli/commands/lineage_upload.py
gable/cli/commands/ping.py
gable/cli/commands/ui.py
gable/cli/converters/mssql.py
gable/cli/converters/mysql.py
gable/cli/helpers/__init__.py
gable/cli/helpers/auth.py
gable/cli/helpers/bundler.py
gable/cli/helpers/contract.py
gable/cli/helpers/data_asset.py
gable/cli/helpers/data_asset_dataframe.py
gable/cli/helpers/data_asset_pyspark.py
gable/cli/helpers/data_asset_s3/__init__.py
gable/cli/helpers/data_asset_s3/actions.py
gable/cli/helpers/data_asset_s3/cache_manager.py
gable/cli/helpers/data_asset_s3/catalog_generator.py
gable-0.56.0.dist-info/METADATA
gable-0.56.0.dist-info/WHEEL
gable-0.56.0.dist-info/entry_points.txt
gable-0.56.0.dist-info/RECORD
