Metadata-Version: 2.3
Name: gable
Version: 0.56.0
Summary: Command line interface (CLI) and software development kit (SDK) to interact with Gable API
Author: Gable.ai
Author-email: engineers@gable.ai
Requires-Python: >=3.10,<4.0
Classifier: Programming Language :: Python :: 3
Classifier: Programming Language :: Python :: 3.10
Classifier: Programming Language :: Python :: 3.11
Classifier: Programming Language :: Python :: 3.12
Classifier: Programming Language :: Python :: 3.13
Provides-Extra: all
Provides-Extra: mssql
Provides-Extra: mysql
Provides-Extra: postgres
Provides-Extra: s3
Requires-Dist: GitPython (>=3.1.0,<4.0.0)
Requires-Dist: boto3 (>=1.34.0,<1.35.0) ; extra == "s3" or extra == "all"
Requires-Dist: botocore (>=1.34.0,<1.35.0) ; extra == "s3" or extra == "all"
Requires-Dist: click (>=8.1.3,<9.0.0)
Requires-Dist: click-option-group (>=0.5.6,<0.6.0)
Requires-Dist: deepdiff (>=8.6.1,<9.0.0) ; extra == "s3" or extra == "all"
Requires-Dist: duckdb (>=1.2.2,<2.0.0) ; extra == "s3" or extra == "all"
Requires-Dist: fastavro (>=1.10.0,<2.0.0) ; extra == "s3" or extra == "all"
Requires-Dist: fsspec (>=2023.0.0,<2025.0.0) ; extra == "s3" or extra == "all"
Requires-Dist: giturlparse (>=0.10.0,<0.11.0)
Requires-Dist: h11 (>=0.16.0,<0.17.0)
Requires-Dist: jsonpickle (>=3.0.0,<4.0.0)
Requires-Dist: jsonref (>=1.1.0,<2.0.0)
Requires-Dist: loguru (>=0.7.0,<0.8.0)
Requires-Dist: mypy-boto3-apigateway (==1.38.0) ; extra == "s3" or extra == "all"
Requires-Dist: mypy-boto3-s3 (>=1.0.0,<2.0.0) ; extra == "s3" or extra == "all"
Requires-Dist: mysql-connector-python (>=9.1.0,<10.0.0) ; extra == "mysql" or extra == "all"
Requires-Dist: numpy (>=1.0.0,<2.0.0) ; extra == "s3" or extra == "all"
Requires-Dist: pandas (>=1.5.3,<3.0.0) ; extra == "s3" or extra == "all"
Requires-Dist: psycopg2-binary (>=2.7) ; extra == "postgres" or extra == "all"
Requires-Dist: pyarrow (>=17.0.0) ; extra == "s3" or extra == "all"
Requires-Dist: pycryptodome (>=3.17.0,<4.0.0)
Requires-Dist: pydantic[email] (>=2.0.0,<3.0.0)
Requires-Dist: pymssql (>=2.2.8,<3.0.0) ; extra == "mssql" or extra == "all"
Requires-Dist: python-snappy (>=0.7.3,<0.8.0) ; extra == "s3" or extra == "all"
Requires-Dist: pyyaml (>=6.0.0,<7.0.0)
Requires-Dist: recap-core[json,proto] (>=0.14.0,<0.15.0) ; python_version >= "3.10" and python_version < "3.15"
Requires-Dist: requests (>=2.31.0,<3.0.0)
Requires-Dist: rich (>=13.5.0,<14.0.0)
Requires-Dist: tqdm (>=4.67.1,<5.0.0)
Requires-Dist: urllib3 (>=2.6.0)
